{
  "hash": "b0b94fef",
  "configHash": "133bdbb5",
  "lockfileHash": "8765f844",
  "browserHash": "430c5d2e",
  "optimized": {
    "@reduxjs/toolkit": {
      "src": "../../node_modules/@reduxjs/toolkit/dist/redux-toolkit.modern.mjs",
      "file": "@reduxjs_toolkit.js",
      "fileHash": "e2dab7c8",
      "needsInterop": false
    },
    "axios": {
      "src": "../../node_modules/axios/index.js",
      "file": "axios.js",
      "fileHash": "855111f6",
      "needsInterop": false
    },
    "react-cookie": {
      "src": "../../node_modules/react-cookie/esm/index.mjs",
      "file": "react-cookie.js",
      "fileHash": "db8e3a62",
      "needsInterop": false
    },
    "react-dom": {
      "src": "../../node_modules/react-dom/index.js",
      "file": "react-dom.js",
      "fileHash": "4b9dc0dd",
      "needsInterop": true
    },
    "react-dom/client": {
      "src": "../../node_modules/react-dom/client.js",
      "file": "react-dom_client.js",
      "fileHash": "2436631f",
      "needsInterop": true
    },
    "react-redux": {
      "src": "../../node_modules/react-redux/dist/react-redux.mjs",
      "file": "react-redux.js",
      "fileHash": "10abeb3e",
      "needsInterop": false
    },
    "react-router-dom": {
      "src": "../../node_modules/react-router-dom/dist/index.mjs",
      "file": "react-router-dom.js",
      "fileHash": "1075da9a",
      "needsInterop": false
    },
    "react": {
      "src": "../../node_modules/react/index.js",
      "file": "react.js",
      "fileHash": "5b896dfb",
      "needsInterop": true
    },
    "react/jsx-dev-runtime": {
      "src": "../../node_modules/react/jsx-dev-runtime.js",
      "file": "react_jsx-dev-runtime.js",
      "fileHash": "1b20082d",
      "needsInterop": true
    },
    "react/jsx-runtime": {
      "src": "../../node_modules/react/jsx-runtime.js",
      "file": "react_jsx-runtime.js",
      "fileHash": "09bc6b5f",
      "needsInterop": true
    }
  },
  "chunks": {
    "chunk-B-1-B7_t": {
      "file": "chunk-B-1-B7_t.js",
      "isDynamicEntry": false
    },
    "react-dom-BRJs3cXW": {
      "file": "react-dom-BRJs3cXW.js",
      "isDynamicEntry": false
    }
  }
}